{"$schema":"http://json-schema.org/draft-07/schema#","$id":"https://poseidat.org/schema/core/ais-message/date-inquiry.json","title":"Request for an UTC date from another ship or station","description":"This message type is used to send and array of binary data as a broadcast","properties":{"ais_message_type":{"description":"The message type of the given AIS measurement","type":"string","enum":["UTC_DATE_INQUIRY"],"default":"UTC_DATE_INQUIRY"},"destination_id":{"description":"The MMSI number where the ship is requisting a date response from.","type":"integer"}},"required":["ais_message_type","destination_id"],"allOf":[{"$ref":"https://poseidat.org/schema/core/ais-message/base-ais-message.json"}],"type":"object","additionalProperties":false}
